secret_sdk/__init__.py
secret_sdk/client/__init__.py
secret_sdk/client/lcd/__init__.py
secret_sdk/client/lcd/api/__init__.py
secret_sdk/client/lcd/api/_base.py
secret_sdk/client/lcd/api/auth.py
secret_sdk/client/lcd/api/authz.py
secret_sdk/client/lcd/api/bank.py
secret_sdk/client/lcd/api/distribution.py
secret_sdk/client/lcd/api/feegrant.py
secret_sdk/client/lcd/api/gov.py
secret_sdk/client/lcd/api/ibc.py
secret_sdk/client/lcd/api/ibc_transfer.py
secret_sdk/client/lcd/api/mint.py
secret_sdk/client/lcd/api/registration.py
secret_sdk/client/lcd/api/slashing.py
secret_sdk/client/lcd/api/staking.py
secret_sdk/client/lcd/api/tendermint.py
secret_sdk/client/lcd/api/tx.py
secret_sdk/client/lcd/api/wasm.py
secret_sdk/client/lcd/lcdclient.py
secret_sdk/client/lcd/params.py
secret_sdk/client/lcd/wallet.py
secret_sdk/client/localsecret.py
secret_sdk/core/__init__.py
secret_sdk/core/auth/__init__.py
secret_sdk/core/auth/data/__init__.py
secret_sdk/core/auth/data/account.py
secret_sdk/core/auth/data/base_account.py
secret_sdk/core/auth/data/base_vesting_account.py
secret_sdk/core/auth/data/continuous_vesting_account.py
secret_sdk/core/auth/data/delayed_vesting_account.py
secret_sdk/core/auth/data/module_account.py
secret_sdk/core/auth/data/params.py
secret_sdk/core/auth/msgs/__init__.py
secret_sdk/core/auth/msgs/msg_create_vesting_account.py
secret_sdk/core/authz/__init__.py
secret_sdk/core/authz/data.py
secret_sdk/core/authz/msgs.py
secret_sdk/core/bank/__init__.py
secret_sdk/core/bank/msgs.py
secret_sdk/core/bech32.py
secret_sdk/core/block.py
secret_sdk/core/broadcast.py
secret_sdk/core/coin.py
secret_sdk/core/coins.py
secret_sdk/core/compact_bit_array.py
secret_sdk/core/crisis/__init__.py
secret_sdk/core/crisis/msgs.py
secret_sdk/core/deposit.py
secret_sdk/core/distribution/__init__.py
secret_sdk/core/distribution/msgs.py
secret_sdk/core/distribution/proposals.py
secret_sdk/core/fee.py
secret_sdk/core/feegrant/__init__.py
secret_sdk/core/feegrant/data.py
secret_sdk_labs-1.8.3.dist-info/LICENSE
secret_sdk_labs-1.8.3.dist-info/METADATA
secret_sdk_labs-1.8.3.dist-info/WHEEL
secret_sdk_labs-1.8.3.dist-info/RECORD
